versionup.py
pyversionup-0.1.5.dist-info/entry_points.txt
pyversionup-0.1.5.dist-info/WHEEL
pyversionup-0.1.5.dist-info/METADATA
pyversionup-0.1.5.dist-info/RECORD
