Metadata-Version: 2.1
Name: pyversionup
Version: 0.1.5
Summary: 
License: MIT
Author: Yohei Tamura
Author-email: tamuhey@gmail.com
Requires-Python: >=3.6,<4.0
Classifier: License :: OSI Approved :: MIT License
Classifier: Programming Language :: Python :: 3
Classifier: Programming Language :: Python :: 3.6
Classifier: Programming Language :: Python :: 3.7
Classifier: Programming Language :: Python :: 3.8
Requires-Dist: dataclasses; python_version < "3.7"
Requires-Dist: fire (>=0.2.1,<0.3.0)
Requires-Dist: toml
Requires-Dist: typing-extensions (>=3.7.4,<4.0.0)
